{
  "project_info": {
    "project_number": "903934021840",
    "firebase_url": "https://visitbpr-7dbbf-default-rtdb.asia-southeast1.firebasedatabase.app",
    "project_id": "visitbpr-7dbbf",
    "storage_bucket": "visitbpr-7dbbf.firebasestorage.app"
  },
  "client": [
    {
      "client_info": {
        "mobilesdk_app_id": "1:903934021840:android:622f994882dbe953584ed5",
        "android_client_info": {
          "package_name": "com.example.visitbpr"
        }
      },
      "oauth_client": [],
      "api_key": [
        {
          "current_key": "AIzaSyDJ0YrVMYSPhuVmZVNXXtL97btg9NRLCyQ"
        }
      ],
      "services": {
        "appinvite_service": {
          "other_platform_oauth_client": []
        }
      }
    }
  ],
  "configuration_version": "1"
}